charmander/__init__.py
charmander/converters.py
charmander/errors.py
charmander/type_mappings.py
charmander-0.2.0.dist-info/licenses/LICENSE
charmander-0.2.0.dist-info/METADATA
charmander-0.2.0.dist-info/WHEEL
charmander-0.2.0.dist-info/top_level.txt
charmander-0.2.0.dist-info/RECORD
