Metadata-Version: 2.4
Name: charmander
Version: 0.2.0
Summary: Convert between Polars schemas and PySpark schemas
Author-email: Odos Matthews <odosmatthews@gmail.com>
License-Expression: MIT
Keywords: polars,pyspark,schema,conversion
Classifier: Development Status :: 3 - Alpha
Classifier: Intended Audience :: Developers
Classifier: Programming Language :: Python :: 3
Classifier: Programming Language :: Python :: 3.8
Classifier: Programming Language :: Python :: 3.9
Classifier: Programming Language :: Python :: 3.10
Classifier: Programming Language :: Python :: 3.11
Classifier: Programming Language :: Python :: 3.12
Requires-Python: >=3.8
License-File: LICENSE
Requires-Dist: polars>=0.19.0
Requires-Dist: pyspark>=3.0.0
Provides-Extra: dev
Requires-Dist: pytest>=7.0.0; extra == "dev"
Requires-Dist: pytest-cov>=4.0.0; extra == "dev"
Requires-Dist: mypy>=1.0.0; extra == "dev"
Requires-Dist: ruff>=0.1.0; extra == "dev"
Requires-Dist: types-pyspark>=3.0.0; extra == "dev"
Dynamic: license-file
